Metadata-Version: 1.0
Name: docxt
Version: 0.1.3
Summary: A simple way to generate a report from a template.
Home-page: https://pypi.org/project/docxt
Author: barwe
Author-email: barwechin@163.com
License: UNKNOWN
Platform: UNKNOWN
